Workbook

Sheet Summary
A1: Little Kettle Shop | Sales Summary
A4: Key numbers | E4: Revenue by country
A5: Revenue | B5: =SUM('Clean Data'!$I$2:$I$301) -> 14306.2 | E5: Country | F5: Orders | G5: Revenue | H5: Share
A6: Orders | B6: =COUNTA('Clean Data'!$A$2:$A$301) -> 300 | E6: Netherlands | F6: =COUNTIFS('Clean Data'!$D$2:$D$301,E6) -> 173 | G6: =SUMIFS('Clean Data'!$I$2:$I$301,'Clean Data'!$D$2:$D$301,E6) -> 7775.25 | H6: =IFERROR(G6/$B$5,0) -> 0.54348814
A7: Items sold | B7: =SUM('Clean Data'!$G$2:$G$301) -> 462 | E7: Germany | F7: =COUNTIFS('Clean Data'!$D$2:$D$301,E7) -> 60 | G7: =SUMIFS('Clean Data'!$I$2:$I$301,'Clean Data'!$D$2:$D$301,E7) -> 3060.95 | H7: =IFERROR(G7/$B$5,0) -> 0.21395968
A8: Average order value | B8: =IFERROR(B5/COUNT('Clean Data'!$I$2:$I$301),0) -> 48.660544 | E8: Belgium | F8: =COUNTIFS('Clean Data'!$D$2:$D$301,E8) -> 43 | G8: =SUMIFS('Clean Data'!$I$2:$I$301,'Clean Data'!$D$2:$D$301,E8) -> 2187.35 | H8: =IFERROR(G8/$B$5,0) -> 0.15289525
A9: Rows flagged for review | B9: =SUMPRODUCT(--('Clean Data'!$L$2:$L$301<>"")) -> 10 | E9: France | F9: =COUNTIFS('Clean Data'!$D$2:$D$301,E9) -> 20 | G9: =SUMIFS('Clean Data'!$I$2:$I$301,'Clean Data'!$D$2:$D$301,E9) -> 1047.95 | H9: =IFERROR(G9/$B$5,0) -> 0.073251457
E10: Missing country | F10: =COUNTIFS('Clean Data'!$D$2:$D$301,"") -> 4
A11: Revenue by month
A12: Month | B12: Orders | C12: Revenue | E12: Revenue by product
A13: 46204 | B13: =COUNTIFS('Clean Data'!$K$2:$K$301,A13) -> 85 | C13: =SUMIFS('Clean Data'!$I$2:$I$301,'Clean Data'!$K$2:$K$301,A13) -> 4599.65 | E13: Product | F13: Qty sold | G13: Revenue
A14: 46235 | B14: =COUNTIFS('Clean Data'!$K$2:$K$301,A14) -> 97 | C14: =SUMIFS('Clean Data'!$I$2:$I$301,'Clean Data'!$K$2:$K$301,A14) -> 4481.55 | E14: =Products!A2 -> French Press 1L | F14: =SUMIFS('Clean Data'!$G$2:$G$301,'Clean Data'!$E$2:$E$301,E14) -> 102 | G14: =SUMIFS('Clean Data'!$I$2:$I$301,'Clean Data'!$E$2:$E$301,E14) -> 2995
A15: 46266 | B15: =COUNTIFS('Clean Data'!$K$2:$K$301,A15) -> 66 | C15: =SUMIFS('Clean Data'!$I$2:$I$301,'Clean Data'!$K$2:$K$301,A15) -> 2728.65 | E15: =Products!A3 -> Ceramic Mug Set (4) | F15: =SUMIFS('Clean Data'!$G$2:$G$301,'Clean Data'!$E$2:$E$301,E15) -> 77 | G15: =SUMIFS('Clean Data'!$I$2:$I$301,'Clean Data'!$E$2:$E$301,E15) -> 1896.2
A16: 46296 | B16: =COUNTIFS('Clean Data'!$K$2:$K$301,A16) -> 52 | C16: =SUMIFS('Clean Data'!$I$2:$I$301,'Clean Data'!$K$2:$K$301,A16) -> 2496.35 | E16: =Products!A4 -> Pour-Over Kettle | F16: =SUMIFS('Clean Data'!$G$2:$G$301,'Clean Data'!$E$2:$E$301,E16) -> 47 | G16: =SUMIFS('Clean Data'!$I$2:$I$301,'Clean Data'!$E$2:$E$301,E16) -> 2303
E17: =Products!A5 -> Coffee Grinder | F17: =SUMIFS('Clean Data'!$G$2:$G$301,'Clean Data'!$E$2:$E$301,E17) -> 46 | G17: =SUMIFS('Clean Data'!$I$2:$I$301,'Clean Data'!$E$2:$E$301,E17) -> 1837.7
E18: =Products!A6 -> Glass Teapot | F18: =SUMIFS('Clean Data'!$G$2:$G$301,'Clean Data'!$E$2:$E$301,E18) -> 43 | G18: =SUMIFS('Clean Data'!$I$2:$I$301,'Clean Data'!$E$2:$E$301,E18) -> 1182.5
E19: =Products!A7 -> Cast Iron Pan 26cm | F19: =SUMIFS('Clean Data'!$G$2:$G$301,'Clean Data'!$E$2:$E$301,E19) -> 29 | G19: =SUMIFS('Clean Data'!$I$2:$I$301,'Clean Data'!$E$2:$E$301,E19) -> 1258.6
E20: =Products!A8 -> Linen Tea Towels (2) | F20: =SUMIFS('Clean Data'!$G$2:$G$301,'Clean Data'!$E$2:$E$301,E20) -> 56 | G20: =SUMIFS('Clean Data'!$I$2:$I$301,'Clean Data'!$E$2:$E$301,E20) -> 725.2
E21: =Products!A9 -> Oak Cutting Board | F21: =SUMIFS('Clean Data'!$G$2:$G$301,'Clean Data'!$E$2:$E$301,E21) -> 62 | G21: =SUMIFS('Clean Data'!$I$2:$I$301,'Clean Data'!$E$2:$E$301,E21) -> 2108

Sheet Clean Data
A1: Order ID | B1: Order Date | C1: Customer | D1: Country | E1: Product | F1: Category | G1: Qty | H1: Unit Price | I1: Total | J1: Payment | K1: Month | L1: Check
A2: LK-2012 | B2: 46207 | C2: Max Dubois | D2: Netherlands | E2: Linen Tea Towels (2) | F2: =IFERROR(INDEX(Products!$B$2:$B$9,MATCH(E2,Products!$A$2:$A$9,0)),"Unknown product") -> Textiles | G2: 1 | H2: 12.95 | I2: =IF(OR(G2="",L2="Price differs from list"),"",G2*H2) -> 12.95 | J2: iDEAL | K2: =DATE(YEAR(B2),MONTH(B2),1) -> 46204 | L2: =IF(G2="","Missing qty",IF(D2="","Missing country",IF(ABS(H2-INDEX(Products!$C$2:$C$9,MATCH(E2,Products!$A$2:$A$9,0)))>0.005,"Price differs from list","")))
A3: LK-2020 | B3: 46210 | C3: Sem Meijer | D3: Germany | E3: Linen Tea Towels (2) | F3: =IFERROR(INDEX(Products!$B$2:$B$9,MATCH(E3,Products!$A$2:$A$9,0)),"Unknown product") -> Textiles | G3: 1 | H3: 12.95 | I3: =IF(OR(G3="",L3="Price differs from list"),"",G3*H3) -> 12.95 | J3: PayPal | K3: =DATE(YEAR(B3),MONTH(B3),1) -> 46204 | L3: =IF(G3="","Missing qty",IF(D3="","Missing country",IF(ABS(H3-INDEX(Products!$C$2:$C$9,MATCH(E3,Products!$A$2:$A$9,0)))>0.005,"Price differs from list","")))
A4: LK-2027 | B4: 46211 | C4: Emma Bakker | D4: Belgium | E4: Linen Tea Towels (2) | F4: =IFERROR(INDEX(Products!$B$2:$B$9,MATCH(E4,Products!$A$2:$A$9,0)),"Unknown product") -> Textiles | G4: 1 | H4: 12.95 | I4: =IF(OR(G4="",L4="Price differs from list"),"",G4*H4) -> 12.95 | J4: Card | K4: =DATE(YEAR(B4),MONTH(B4),1) -> 46204 | L4: =IF(G4="","Missing qty",IF(D4="","Missing country",IF(ABS(H4-INDEX(Products!$C$2:$C$9,MATCH(E4,Products!$A$2:$A$9,0)))>0.005,"Price differs from list","")))
A5: LK-2054 | B5: 46220 | C5: Lea Peeters | D5: Belgium | E5: Linen Tea Towels (2) | F5: =IFERROR(INDEX(Products!$B$2:$B$9,MATCH(E5,Products!$A$2:$A$9,0)),"Unknown product") -> Textiles | G5: 1 | H5: 12.95 | I5: =IF(OR(G5="",L5="Price differs from list"),"",G5*H5) -> 12.95 | J5: Card | K5: =DATE(YEAR(B5),MONTH(B5),1) -> 46204 | L5: =IF(G5="","Missing qty",IF(D5="","Missing country",IF(ABS(H5-INDEX(Products!$C$2:$C$9,MATCH(E5,Products!$A$2:$A$9,0)))>0.005,"Price differs from list","")))
A6: LK-2071 | B6: 46229 | C6: Sophie Bos | D6: Netherlands | E6: Linen Tea Towels (2) | F6: =IFERROR(INDEX(Products!$B$2:$B$9,MATCH(E6,Products!$A$2:$A$9,0)),"Unknown product") -> Textiles | G6: 1 | H6: 12.95 | I6: =IF(OR(G6="",L6="Price differs from list"),"",G6*H6) -> 12.95 | J6: PayPal | K6: =DATE(YEAR(B6),MONTH(B6),1) -> 46204 | L6: =IF(G6="","Missing qty",IF(D6="","Missing country",IF(ABS(H6-INDEX(Products!$C$2:$C$9,MATCH(E6,Products!$A$2:$A$9,0)))>0.005,"Price differs from list","")))
A7: LK-2088 | B7: 46235 | C7: Noah Dubois | D7: Netherlands | E7: Linen Tea Towels (2) | F7: =IFERROR(INDEX(Products!$B$2:$B$9,MATCH(E7,Products!$A$2:$A$9,0)),"Unknown product") -> Textiles | G7: 1 | H7: 12.95 | I7: =IF(OR(G7="",L7="Price differs from list"),"",G7*H7) -> 12.95 | J7: iDEAL | K7: =DATE(YEAR(B7),MONTH(B7),1) -> 46235 | L7: =IF(G7="","Missing qty",IF(D7="","Missing country",IF(ABS(H7-INDEX(Products!$C$2:$C$9,MATCH(E7,Products!$A$2:$A$9,0)))>0.005,"Price differs from list","")))
A8: LK-2091 | B8: 46236 | C8: Emma Jansen | D8: France | E8: Linen Tea Towels (2) | F8: =IFERROR(INDEX(Products!$B$2:$B$9,MATCH(E8,Products!$A$2:$A$9,0)),"Unknown product") -> Textiles | G8: 1 | H8: 12.95 | I8: =IF(OR(G8="",L8="Price differs from list"),"",G8*H8) -> 12.95 | J8: Card | K8: =DATE(YEAR(B8),MONTH(B8),1) -> 46235 | L8: =IF(G8="","Missing qty",IF(D8="","Missing country",IF(ABS(H8-INDEX(Products!$C$2:$C$9,MATCH(E8,Products!$A$2:$A$9,0)))>0.005,"Price differs from list","")))
A9: LK-2109 | B9: 46243 | C9: Finn Visser | D9: Netherlands | E9: Linen Tea Towels (2) | F9: =IFERROR(INDEX(Products!$B$2:$B$9,MATCH(E9,Products!$A$2:$A$9,0)),"Unknown product") -> Textiles | G9: 1 | H9: 12.95 | I9: =IF(OR(G9="",L9="Price differs from list"),"",G9*H9) -> 12.95 | J9: Card | K9: =DATE(YEAR(B9),MONTH(B9),1) -> 46235 | L9: =IF(G9="","Missing qty",IF(D9="","Missing country",IF(ABS(H9-INDEX(Products!$C$2:$C$9,MATCH(E9,Products!$A$2:$A$9,0)))>0.005,"Price differs from list","")))
A10: LK-2133 | B10: 46251 | C10: Anna de Vries | D10: Netherlands | E10: Linen Tea Towels (2) | F10: =IFERROR(INDEX(Products!$B$2:$B$9,MATCH(E10,Products!$A$2:$A$9,0)),"Unknown product") -> Textiles | G10: 1 | H10: 12.95 | I10: =IF(OR(G10="",L10="Price differs from list"),"",G10*H10) -> 12.95 | J10: Card | K10: =DATE(YEAR(B10),MONTH(B10),1) -> 46235 | L10: =IF(G10="","Missing qty",IF(D10="","Missing country",IF(ABS(H10-INDEX(Products!$C$2:$C$9,MATCH(E10,Products!$A$2:$A$9,0)))>0.005,"Price differs from list","")))
A11: LK-2162 | B11: 46259 | C11: Marie Hendriks | D11: Netherlands | E11: Linen Tea Towels (2) | F11: =IFERROR(INDEX(Products!$B$2:$B$9,MATCH(E11,Products!$A$2:$A$9,0)),"Unknown product") -> Textiles | G11: 1 | H11: 12.95 | I11: =IF(OR(G11="",L11="Price differs from list"),"",G11*H11) -> 12.95 | J11: Card | K11: =DATE(YEAR(B11),MONTH(B11),1) -> 46235 | L11: =IF(G11="","Missing qty",IF(D11="","Missing country",IF(ABS(H11-INDEX(Products!$C$2:$C$9,MATCH(E11,Products!$A$2:$A$9,0)))>0.005,"Price differs from list","")))
A12: LK-2166 | B12: 46262 | C12: Lotte Bakker | D12: Netherlands | E12: Linen Tea Towels (2) | F12: =IFERROR(INDEX(Products!$B$2:$B$9,MATCH(E12,Products!$A$2:$A$9,0)),"Unknown product") -> Textiles | G12: 1 | H12: 12.95 | I12: =IF(OR(G12="",L12="Price differs from list"),"",G12*H12) -> 12.95 | J12: Card | K12: =DATE(YEAR(B12),MONTH(B12),1) -> 46235 | L12: =IF(G12="","Missing qty",IF(D12="","Missing country",IF(ABS(H12-INDEX(Products!$C$2:$C$9,MATCH(E12,Products!$A$2:$A$9,0)))>0.005,"Price differs from list","")))
A13: LK-2175 | B13: 46265 | C13: Nora Müller | D13: Netherlands | E13: Linen Tea Towels (2) | F13: =IFERROR(INDEX(Products!$B$2:$B$9,MATCH(E13,Products!$A$2:$A$9,0)),"Unknown product") -> Textiles | G13: 1 | H13: 12.95 | I13: =IF(OR(G13="",L13="Price differs from list"),"",G13*H13) -> 12.95 | J13: iDEAL | K13: =DATE(YEAR(B13),MONTH(B13),1) -> 46235 | L13: =IF(G13="","Missing qty",IF(D13="","Missing country",IF(ABS(H13-INDEX(Products!$C$2:$C$9,MATCH(E13,Products!$A$2:$A$9,0)))>0.005,"Price differs from list","")))
... A88: LK-2163 | B88: 46260 | C88: Sara Dubois | D88: Germany | E88: Ceramic Mug Set (4) | F88: =IFERROR(INDEX(Products!$B$2:$B$9,MATCH(E88,Products!$A$2:$A$9,0)),"Unknown product") -> Tableware | G88: 4 | H88: 24.95 | I88: =IF(OR(G88="",L88="Price differs from list"),"",G88*H88) -> 99.8 | J88: Card | K88: =DATE(YEAR(B88),MONTH(B88),1) -> 46235 | L88: =IF(G88="","Missing qty",IF(D88="","Missing country",IF(ABS(H88-INDEX(Products!$C$2:$C$9,MATCH(E88,Products!$A$2:$A$9,0)))>0.005,"Price differs from list","")))
A89: LK-2086 | B89: 46235 | C89: Emma Bakker | D89: Netherlands | E89: Ceramic Mug Set (4) | F89: =IFERROR(INDEX(Products!$B$2:$B$9,MATCH(E89,Products!$A$2:$A$9,0)),"Unknown product") -> Tableware | H89: 24.95 | I89: =IF(OR(G89="",L89="Price differs from list"),"",G89*H89) | J89: PayPal | K89: =DATE(YEAR(B89),MONTH(B89),1) -> 46235 | L89: =IF(G89="","Missing qty",IF(D89="","Missing country",IF(ABS(H89-INDEX(Products!$C$2:$C$9,MATCH(E89,Products!$A$2:$A$9,0)))>0.005,"Price differs from list",""))) -> Missing qty
A90: LK-2030 | B90: 46212 | C90: Sem Visser | D90: Netherlands | E90: Glass Teapot | F90: =IFERROR(INDEX(Products!$B$2:$B$9,MATCH(E90,Products!$A$2:$A$9,0)),"Unknown product") -> Tea | G90: 1 | H90: 27.5 | I90: =IF(OR(G90="",L90="Price differs from list"),"",G90*H90) -> 27.5 | J90: Card | K90: =DATE(YEAR(B90),MONTH(B90),1) -> 46204 | L90: =IF(G90="","Missing qty",IF(D90="","Missing country",IF(ABS(H90-INDEX(Products!$C$2:$C$9,MATCH(E90,Products!$A$2:$A$9,0)))>0.005,"Price differs from list","")))
A91: LK-2043 | B91: 46215 | C91: Claire Hendriks | D91: Netherlands | E91: Glass Teapot | F91: =IFERROR(INDEX(Products!$B$2:$B$9,MATCH(E91,Products!$A$2:$A$9,0)),"Unknown product") -> Tea | G91: 1 | H91: 27.5 | I91: =IF(OR(G91="",L91="Price differs from list"),"",G91*H91) -> 27.5 | J91: iDEAL | K91: =DATE(YEAR(B91),MONTH(B91),1) -> 46204 | L91: =IF(G91="","Missing qty",IF(D91="","Missing country",IF(ABS(H91-INDEX(Products!$C$2:$C$9,MATCH(E91,Products!$A$2:$A$9,0)))>0.005,"Price differs from list","")))
A92: LK-2053 | B92: 46220 | C92: Noah Bakker | D92: Netherlands | E92: Glass Teapot | F92: =IFERROR(INDEX(Products!$B$2:$B$9,MATCH(E92,Products!$A$2:$A$9,0)),"Unknown product") -> Tea | G92: 1 | H92: 27.5 | I92: =IF(OR(G92="",L92="Price differs from list"),"",G92*H92) -> 27.5 | J92: iDEAL | K92: =DATE(YEAR(B92),MONTH(B92),1) -> 46204 | L92: =IF(G92="","Missing qty",IF(D92="","Missing country",IF(ABS(H92-INDEX(Products!$C$2:$C$9,MATCH(E92,Products!$A$2:$A$9,0)))>0.005,"Price differs from list","")))
A93: LK-2090 | B93: 46236 | C93: Eva Müller | D93: Belgium | E93: Glass Teapot | F93: =IFERROR(INDEX(Products!$B$2:$B$9,MATCH(E93,Products!$A$2:$A$9,0)),"Unknown product") -> Tea | G93: 1 | H93: 27.5 | I93: =IF(OR(G93="",L93="Price differs from list"),"",G93*H93) -> 27.5 | J93: Card | K93: =DATE(YEAR(B93),MONTH(B93),1) -> 46235 | L93: =IF(G93="","Missing qty",IF(D93="","Missing country",IF(ABS(H93-INDEX(Products!$C$2:$C$9,MATCH(E93,Products!$A$2:$A$9,0)))>0.005,"Price differs from list","")))
A94: LK-2108 | B94: 46243 | C94: Claire Meijer | D94: Netherlands | E94: Glass Teapot | F94: =IFERROR(INDEX(Products!$B$2:$B$9,MATCH(E94,Products!$A$2:$A$9,0)),"Unknown product") -> Tea | G94: 1 | H94: 27.5 | I94: =IF(OR(G94="",L94="Price differs from list"),"",G94*H94) -> 27.5 | J94: PayPal | K94: =DATE(YEAR(B94),MONTH(B94),1) -> 46235 | L94: =IF(G94="","Missing qty",IF(D94="","Missing country",IF(ABS(H94-INDEX(Products!$C$2:$C$9,MATCH(E94,Products!$A$2:$A$9,0)))>0.005,"Price differs from list","")))
A95: LK-2121 | B95: 46248 | C95: Levi Bos | D95: Germany | E95: Glass Teapot | F95: =IFERROR(INDEX(Products!$B$2:$B$9,MATCH(E95,Products!$A$2:$A$9,0)),"Unknown product") -> Tea | G95: 1 | H95: 27.5 | I95: =IF(OR(G95="",L95="Price differs from list"),"",G95*H95) -> 27.5 | J95: Card | K95: =DATE(YEAR(B95),MONTH(B95),1) -> 46235 | L95: =IF(G95="","Missing qty",IF(D95="","Missing country",IF(ABS(H95-INDEX(Products!$C$2:$C$9,MATCH(E95,Products!$A$2:$A$9,0)))>0.005,"Price differs from list","")))
A96: LK-2122 | B96: 46248 | C96: Jonas Schmidt | D96: Belgium | E96: Glass Teapot | F96: =IFERROR(INDEX(Products!$B$2:$B$9,MATCH(E96,Products!$A$2:$A$9,0)),"Unknown product") -> Tea | G96: 1 | H96: 27.5 | I96: =IF(OR(G96="",L96="Price differs from list"),"",G96*H96) -> 27.5 | J96: Card | K96: =DATE(YEAR(B96),MONTH(B96),1) -> 46235 | L96: =IF(G96="","Missing qty",IF(D96="","Missing country",IF(ABS(H96-INDEX(Products!$C$2:$C$9,MATCH(E96,Products!$A$2:$A$9,0)))>0.005,"Price differs from list","")))
A97: LK-2139 | B97: 46253 | C97: Lea Martin | D97: Netherlands | E97: Glass Teapot | F97: =IFERROR(INDEX(Products!$B$2:$B$9,MATCH(E97,Products!$A$2:$A$9,0)),"Unknown product") -> Tea | G97: 1 | H97: 27.5 | I97: =IF(OR(G97="",L97="Price differs from list"),"",G97*H97) -> 27.5 | J97: Card | K97: =DATE(YEAR(B97),MONTH(B97),1) -> 46235 | L97: =IF(G97="","Missing qty",IF(D97="","Missing country",IF(ABS(H97-INDEX(Products!$C$2:$C$9,MATCH(E97,Products!$A$2:$A$9,0)))>0.005,"Price differs from list","")))
A98: LK-2190 | B98: 46269 | C98: Anna Wagner | D98: Netherlands | E98: Glass Teapot | F98: =IFERROR(INDEX(Products!$B$2:$B$9,MATCH(E98,Products!$A$2:$A$9,0)),"Unknown product") -> Tea | G98: 1 | H98: 27.5 | I98: =IF(OR(G98="",L98="Price differs from list"),"",G98*H98) -> 27.5 | J98: iDEAL | K98: =DATE(YEAR(B98),MONTH(B98),1) -> 46266 | L98: =IF(G98="","Missing qty",IF(D98="","Missing country",IF(ABS(H98-INDEX(Products!$C$2:$C$9,MATCH(E98,Products!$A$2:$A$9,0)))>0.005,"Price differs from list","")))
A99: LK-2205 | B99: 46277 | C99: Julia Hendriks | D99: Netherlands | E99: Glass Teapot | F99: =IFERROR(INDEX(Products!$B$2:$B$9,MATCH(E99,Products!$A$2:$A$9,0)),"Unknown product") -> Tea | G99: 1 | H99: 27.5 | I99: =IF(OR(G99="",L99="Price differs from list"),"",G99*H99) -> 27.5 | J99: PayPal | K99: =DATE(YEAR(B99),MONTH(B99),1) -> 46266 | L99: =IF(G99="","Missing qty",IF(D99="","Missing country",IF(ABS(H99-INDEX(Products!$C$2:$C$9,MATCH(E99,Products!$A$2:$A$9,0)))>0.005,"Price differs from list","")))
A100: LK-2207 | B100: 46277 | C100: Finn Meijer | D100: Netherlands | E100: Glass Teapot | F100: =IFERROR(INDEX(Products!$B$2:$B$9,MATCH(E100,Products!$A$2:$A$9,0)),"Unknown product") -> Tea | G100: 1 | H100: 27.5 | I100: =IF(OR(G100="",L100="Price differs from list"),"",G100*H100) -> 27.5 | J100: Card | K100: =DATE(YEAR(B100),MONTH(B100),1) -> 46266 | L100: =IF(G100="","Missing qty",IF(D100="","Missing country",IF(ABS(H100-INDEX(Products!$C$2:$C$9,MATCH(E100,Products!$A$2:$A$9,0)))>0.005,"Price differs from list","")))
A101: LK-2210 | B101: 46277 | C101: Liam Martin | D101: Netherlands | E101: Glass Teapot | F101: =IFERROR(INDEX(Products!$B$2:$B$9,MATCH(E101,Products!$A$2:$A$9,0)),"Unknown product") -> Tea | G101: 1 | H101: 27.5 | I101: =IF(OR(G101="",L101="Price differs from list"),"",G101*H101) -> 27.5 | J101: Card | K101: =DATE(YEAR(B101),MONTH(B101),1) -> 46266 | L101: =IF(G101="","Missing qty",IF(D101="","Missing country",IF(ABS(H101-INDEX(Products!$C$2:$C$9,MATCH(E101,Products!$A$2:$A$9,0)))>0.005,"Price differs from list","")))
... A137: LK-2218 | B137: 46280 | C137: Julia Maes | D137: Netherlands | E137: French Press 1L | F137: =IFERROR(INDEX(Products!$B$2:$B$9,MATCH(E137,Products!$A$2:$A$9,0)),"Unknown product") -> Coffee | G137: 1 | H137: 29.95 | I137: =IF(OR(G137="",L137="Price differs from list"),"",G137*H137) -> 29.95 | J137: iDEAL | K137: =DATE(YEAR(B137),MONTH(B137),1) -> 46266 | L137: =IF(G137="","Missing qty",IF(D137="","Missing country",IF(ABS(H137-INDEX(Products!$C$2:$C$9,MATCH(E137,Products!$A$2:$A$9,0)))>0.005,"Price differs from list","")))
A138: LK-2237 | B138: 46290 | C138: Hugo Visser | E138: French Press 1L | F138: =IFERROR(INDEX(Products!$B$2:$B$9,MATCH(E138,Products!$A$2:$A$9,0)),"Unknown product") -> Coffee | G138: 1 | H138: 29.95 | I138: =IF(OR(G138="",L138="Price differs from list"),"",G138*H138) -> 29.95 | J138: Card | K138: =DATE(YEAR(B138),MONTH(B138),1) -> 46266 | L138: =IF(G138="","Missing qty",IF(D138="","Missing country",IF(ABS(H138-INDEX(Products!$C$2:$C$9,MATCH(E138,Products!$A$2:$A$9,0)))>0.005,"Price differs from list",""))) -> Missing country
A139: LK-2241 | B139: 46292 | C139: Liam Hendriks | D139: Netherlands | E139: French Press 1L | F139: =IFERROR(INDEX(Products!$B$2:$B$9,MATCH(E139,Products!$A$2:$A$9,0)),"Unknown product") -> Coffee | G139: 1 | H139: 29.95 | I139: =IF(OR(G139="",L139="Price differs from list"),"",G139*H139) -> 29.95 | J139: PayPal | K139: =DATE(YEAR(B139),MONTH(B139),1) -> 46266 | L139: =IF(G139="","Missing qty",IF(D139="","Missing country",IF(ABS(H139-INDEX(Products!$C$2:$C$9,MATCH(E139,Products!$A$2:$A$9,0)))>0.005,"Price differs from list","")))
A140: LK-2249 | B140: 46296 | C140: Lucas Bos | D140: Netherlands | E140: French Press 1L | F140: =IFERROR(INDEX(Products!$B$2:$B$9,MATCH(E140,Products!$A$2:$A$9,0)),"Unknown product") -> Coffee | G140: 1 | H140: 29.95 | I140: =IF(OR(G140="",L140="Price differs from list"),"",G140*H140) -> 29.95 | J140: PayPal | K140: =DATE(YEAR(B140),MONTH(B140),1) -> 46296 | L140: =IF(G140="","Missing qty",IF(D140="","Missing country",IF(ABS(H140-INDEX(Products!$C$2:$C$9,MATCH(E140,Products!$A$2:$A$9,0)))>0.005,"Price differs from list","")))
A141: LK-2250 | B141: 46297 | C141: Sem Maes | D141: Netherlands | E141: French Press 1L | F141: =IFERROR(INDEX(Products!$B$2:$B$9,MATCH(E141,Products!$A$2:$A$9,0)),"Unknown product") -> Coffee | G141: 1 | H141: 29.95 | I141: =IF(OR(G141="",L141="Price differs from list"),"",G141*H141) -> 29.95 | J141: iDEAL | K141: =DATE(YEAR(B141),MONTH(B141),1) -> 46296 | L141: =IF(G141="","Missing qty",IF(D141="","Missing country",IF(ABS(H141-INDEX(Products!$C$2:$C$9,MATCH(E141,Products!$A$2:$A$9,0)))>0.005,"Price differs from list","")))
A142: LK-2255 | B142: 46299 | C142: Emma Bakker | E142: French Press 1L | F142: =IFERROR(INDEX(Products!$B$2:$B$9,MATCH(E142,Products!$A$2:$A$9,0)),"Unknown product") -> Coffee | G142: 1 | H142: 29.95 | I142: =IF(OR(G142="",L142="Price differs from list"),"",G142*H142) -> 29.95 | J142: iDEAL | K142: =DATE(YEAR(B142),MONTH(B142),1) -> 46296 | L142: =IF(G142="","Missing qty",IF(D142="","Missing country",IF(ABS(H142-INDEX(Products!$C$2:$C$9,MATCH(E142,Products!$A$2:$A$9,0)))>0.005,"Price differs from list",""))) -> Missing country
A143: LK-2298 | B143: 46315 | C143: Eva Meijer | D143: Netherlands | E143: French Press 1L | F143: =IFERROR(INDEX(Products!$B$2:$B$9,MATCH(E143,Products!$A$2:$A$9,0)),"Unknown product") -> Coffee | G143: 1 | H143: 29.95 | I143: =IF(OR(G143="",L143="Price differs from list"),"",G143*H143) -> 29.95 | J143: PayPal | K143: =DATE(YEAR(B143),MONTH(B143),1) -> 46296 | L143: =IF(G143="","Missing qty",IF(D143="","Missing country",IF(ABS(H143-INDEX(Products!$C$2:$C$9,MATCH(E143,Products!$A$2:$A$9,0)))>0.005,"Price differs from list","")))
A144: LK-2300 | B144: 46315 | C144: Lena Hendriks | D144: Netherlands | E144: French Press 1L | F144: =IFERROR(INDEX(Products!$B$2:$B$9,MATCH(E144,Products!$A$2:$A$9,0)),"Unknown product") -> Coffee | G144: 1 | H144: 29.95 | I144: =IF(OR(G144="",L144="Price differs from list"),"",G144*H144) -> 29.95 | J144: Card | K144: =DATE(YEAR(B144),MONTH(B144),1) -> 46296 | L144: =IF(G144="","Missing qty",IF(D144="","Missing country",IF(ABS(H144-INDEX(Products!$C$2:$C$9,MATCH(E144,Products!$A$2:$A$9,0)))>0.005,"Price differs from list","")))
A145: LK-2013 | B145: 46207 | C145: Marie Jansen | D145: Germany | E145: French Press 1L | F145: =IFERROR(INDEX(Products!$B$2:$B$9,MATCH(E145,Products!$A$2:$A$9,0)),"Unknown product") -> Coffee | G145: 2 | H145: 29.95 | I145: =IF(OR(G145="",L145="Price differs from list"),"",G145*H145) -> 59.9 | J145: PayPal | K145: =DATE(YEAR(B145),MONTH(B145),1) -> 46204 | L145: =IF(G145="","Missing qty",IF(D145="","Missing country",IF(ABS(H145-INDEX(Products!$C$2:$C$9,MATCH(E145,Products!$A$2:$A$9,0)))>0.005,"Price differs from list","")))
A146: LK-2016 | B146: 46208 | C146: Paul Hendriks | D146: Belgium | E146: French Press 1L | F146: =IFERROR(INDEX(Products!$B$2:$B$9,MATCH(E146,Products!$A$2:$A$9,0)),"Unknown product") -> Coffee | G146: 2 | H146: 29.95 | I146: =IF(OR(G146="",L146="Price differs from list"),"",G146*H146) -> 59.9 | J146: PayPal | K146: =DATE(YEAR(B146),MONTH(B146),1) -> 46204 | L146: =IF(G146="","Missing qty",IF(D146="","Missing country",IF(ABS(H146-INDEX(Products!$C$2:$C$9,MATCH(E146,Products!$A$2:$A$9,0)))>0.005,"Price differs from list","")))
A147: LK-2028 | B147: 46211 | C147: Finn Bos | D147: Belgium | E147: French Press 1L | F147: =IFERROR(INDEX(Products!$B$2:$B$9,MATCH(E147,Products!$A$2:$A$9,0)),"Unknown product") -> Coffee | G147: 2 | H147: 29.95 | I147: =IF(OR(G147="",L147="Price differs from list"),"",G147*H147) -> 59.9 | J147: PayPal | K147: =DATE(YEAR(B147),MONTH(B147),1) -> 46204 | L147: =IF(G147="","Missing qty",IF(D147="","Missing country",IF(ABS(H147-INDEX(Products!$C$2:$C$9,MATCH(E147,Products!$A$2:$A$9,0)))>0.005,"Price differs from list","")))
A148: LK-2048 | B148: 46219 | C148: Sophie Müller | D148: Belgium | E148: French Press 1L | F148: =IFERROR(INDEX(Products!$B$2:$B$9,MATCH(E148,Products!$A$2:$A$9,0)),"Unknown product") -> Coffee | G148: 2 | H148: 29.95 | I148: =IF(OR(G148="",L148="Price differs from list"),"",G148*H148) -> 59.9 | J148: Card | K148: =DATE(YEAR(B148),MONTH(B148),1) -> 46204 | L148: =IF(G148="","Missing qty",IF(D148="","Missing country",IF(ABS(H148-INDEX(Products!$C$2:$C$9,MATCH(E148,Products!$A$2:$A$9,0)))>0.005,"Price differs from list","")))
A149: LK-2050 | B149: 46220 | C149: Marie Smit | D149: Germany | E149: French Press 1L | F149: =IFERROR(INDEX(Products!$B$2:$B$9,MATCH(E149,Products!$A$2:$A$9,0)),"Unknown product") -> Coffee | G149: 2 | H149: 29.95 | I149: =IF(OR(G149="",L149="Price differs from list"),"",G149*H149) -> 59.9 | J149: Card | K149: =DATE(YEAR(B149),MONTH(B149),1) -> 46204 | L149: =IF(G149="","Missing qty",IF(D149="","Missing country",IF(ABS(H149-INDEX(Products!$C$2:$C$9,MATCH(E149,Products!$A$2:$A$9,0)))>0.005,"Price differs from list","")))
A150: LK-2052 | B150: 46220 | C150: Lena Martin | D150: Belgium | E150: French Press 1L | F150: =IFERROR(INDEX(Products!$B$2:$B$9,MATCH(E150,Products!$A$2:$A$9,0)),"Unknown product") -> Coffee | G150: 2 | H150: 29.95 | I150: =IF(OR(G150="",L150="Price differs from list"),"",G150*H150) -> 59.9 | J150: Card | K150: =DATE(YEAR(B150),MONTH(B150),1) -> 46204 | L150: =IF(G150="","Missing qty",IF(D150="","Missing country",IF(ABS(H150-INDEX(Products!$C$2:$C$9,MATCH(E150,Products!$A$2:$A$9,0)))>0.005,"Price differs from list","")))
A151: LK-2079 | B151: 46231 | C151: Noah Dubois | D151: France | E151: French Press 1L | F151: =IFERROR(INDEX(Products!$B$2:$B$9,MATCH(E151,Products!$A$2:$A$9,0)),"Unknown product") -> Coffee | G151: 2 | H151: 29.95 | I151: =IF(OR(G151="",L151="Price differs from list"),"",G151*H151) -> 59.9 | J151: Card | K151: =DATE(YEAR(B151),MONTH(B151),1) -> 46204 | L151: =IF(G151="","Missing qty",IF(D151="","Missing country",IF(ABS(H151-INDEX(Products!$C$2:$C$9,MATCH(E151,Products!$A$2:$A$9,0)))>0.005,"Price differs from list","")))
A152: LK-2120 | B152: 46247 | C152: Jonas Mulder | D152: Netherlands | E152: French Press 1L | F152: =IFERROR(INDEX(Products!$B$2:$B$9,MATCH(E152,Products!$A$2:$A$9,0)),"Unknown product") -> Coffee | G152: 2 | H152: 29.95 | I152: =IF(OR(G152="",L152="Price differs from list"),"",G152*H152) -> 59.9 | J152: iDEAL | K152: =DATE(YEAR(B152),MONTH(B152),1) -> 46235 | L152: =IF(G152="","Missing qty",IF(D152="","Missing country",IF(ABS(H152-INDEX(Products!$C$2:$C$9,MATCH(E152,Products!$A$2:$A$9,0)))>0.005,"Price differs from list","")))
A153: LK-2135 | B153: 46252 | C153: Paul Müller | D153: Netherlands | E153: French Press 1L | F153: =IFERROR(INDEX(Products!$B$2:$B$9,MATCH(E153,Products!$A$2:$A$9,0)),"Unknown product") -> Coffee | G153: 2 | H153: 29.95 | I153: =IF(OR(G153="",L153="Price differs from list"),"",G153*H153) -> 59.9 | J153: PayPal | K153: =DATE(YEAR(B153),MONTH(B153),1) -> 46235 | L153: =IF(G153="","Missing qty",IF(D153="","Missing country",IF(ABS(H153-INDEX(Products!$C$2:$C$9,MATCH(E153,Products!$A$2:$A$9,0)))>0.005,"Price differs from list","")))
A154: LK-2144 | B154: 46254 | C154: Marie Bos | D154: Netherlands | E154: French Press 1L | F154: =IFERROR(INDEX(Products!$B$2:$B$9,MATCH(E154,Products!$A$2:$A$9,0)),"Unknown product") -> Coffee | G154: 2 | H154: 29.95 | I154: =IF(OR(G154="",L154="Price differs from list"),"",G154*H154) -> 59.9 | J154: Card | K154: =DATE(YEAR(B154),MONTH(B154),1) -> 46235 | L154: =IF(G154="","Missing qty",IF(D154="","Missing country",IF(ABS(H154-INDEX(Products!$C$2:$C$9,MATCH(E154,Products!$A$2:$A$9,0)))>0.005,"Price differs from list","")))
... A175: LK-2288 | B175: 46310 | C175: Jonas Martin | D175: France | E175: French Press 1L | F175: =IFERROR(INDEX(Products!$B$2:$B$9,MATCH(E175,Products!$A$2:$A$9,0)),"Unknown product") -> Coffee | G175: 3 | H175: 29.95 | I175: =IF(OR(G175="",L175="Price differs from list"),"",G175*H175) -> 89.85 | J175: Card | K175: =DATE(YEAR(B175),MONTH(B175),1) -> 46296 | L175: =IF(G175="","Missing qty",IF(D175="","Missing country",IF(ABS(H175-INDEX(Products!$C$2:$C$9,MATCH(E175,Products!$A$2:$A$9,0)))>0.005,"Price differs from list","")))
A176: LK-2134 | B176: 46252 | C176: Marie Bakker | D176: France | E176: French Press 1L | F176: =IFERROR(INDEX(Products!$B$2:$B$9,MATCH(E176,Products!$A$2:$A$9,0)),"Unknown product") -> Coffee | H176: 29.95 | I176: =IF(OR(G176="",L176="Price differs from list"),"",G176*H176) | J176: Card | K176: =DATE(YEAR(B176),MONTH(B176),1) -> 46235 | L176: =IF(G176="","Missing qty",IF(D176="","Missing country",IF(ABS(H176-INDEX(Products!$C$2:$C$9,MATCH(E176,Products!$A$2:$A$9,0)))>0.005,"Price differs from list",""))) -> Missing qty
A177: LK-2006 | B177: 46205 | C177: Paul Smit | D177: Netherlands | E177: Oak Cutting Board | F177: =IFERROR(INDEX(Products!$B$2:$B$9,MATCH(E177,Products!$A$2:$A$9,0)),"Unknown product") -> Cookware | G177: 1 | H177: 34 | I177: =IF(OR(G177="",L177="Price differs from list"),"",G177*H177) -> 34 | J177: Card | K177: =DATE(YEAR(B177),MONTH(B177),1) -> 46204 | L177: =IF(G177="","Missing qty",IF(D177="","Missing country",IF(ABS(H177-INDEX(Products!$C$2:$C$9,MATCH(E177,Products!$A$2:$A$9,0)))>0.005,"Price differs from list","")))
A178: LK-2018 | B178: 46209 | C178: Claire Peters | D178: Belgium | E178: Oak Cutting Board | F178: =IFERROR(INDEX(Products!$B$2:$B$9,MATCH(E178,Products!$A$2:$A$9,0)),"Unknown product") -> Cookware | G178: 1 | H178: 34 | I178: =IF(OR(G178="",L178="Price differs from list"),"",G178*H178) -> 34 | J178: PayPal | K178: =DATE(YEAR(B178),MONTH(B178),1) -> 46204 | L178: =IF(G178="","Missing qty",IF(D178="","Missing country",IF(ABS(H178-INDEX(Products!$C$2:$C$9,MATCH(E178,Products!$A$2:$A$9,0)))>0.005,"Price differs from list","")))
A179: LK-2029 | B179: 46211 | C179: Mila Smit | D179: Germany | E179: Oak Cutting Board | F179: =IFERROR(INDEX(Products!$B$2:$B$9,MATCH(E179,Products!$A$2:$A$9,0)),"Unknown product") -> Cookware | G179: 1 | H179: 34 | I179: =IF(OR(G179="",L179="Price differs from list"),"",G179*H179) -> 34 | J179: PayPal | K179: =DATE(YEAR(B179),MONTH(B179),1) -> 46204 | L179: =IF(G179="","Missing qty",IF(D179="","Missing country",IF(ABS(H179-INDEX(Products!$C$2:$C$9,MATCH(E179,Products!$A$2:$A$9,0)))>0.005,"Price differs from list","")))
A180: LK-2037 | B180: 46214 | C180: Eva Peters | D180: Netherlands | E180: Oak Cutting Board | F180: =IFERROR(INDEX(Products!$B$2:$B$9,MATCH(E180,Products!$A$2:$A$9,0)),"Unknown product") -> Cookware | G180: 1 | H180: 34 | I180: =IF(OR(G180="",L180="Price differs from list"),"",G180*H180) -> 34 | J180: iDEAL | K180: =DATE(YEAR(B180),MONTH(B180),1) -> 46204 | L180: =IF(G180="","Missing qty",IF(D180="","Missing country",IF(ABS(H180-INDEX(Products!$C$2:$C$9,MATCH(E180,Products!$A$2:$A$9,0)))>0.005,"Price differs from list","")))
A181: LK-2039 | B181: 46214 | C181: Marie Dubois | D181: Netherlands | E181: Oak Cutting Board | F181: =IFERROR(INDEX(Products!$B$2:$B$9,MATCH(E181,Products!$A$2:$A$9,0)),"Unknown product") -> Cookware | G181: 1 | H181: 34 | I181: =IF(OR(G181="",L181="Price differs from list"),"",G181*H181) -> 34 | J181: iDEAL | K181: =DATE(YEAR(B181),MONTH(B181),1) -> 46204 | L181: =IF(G181="","Missing qty",IF(D181="","Missing country",IF(ABS(H181-INDEX(Products!$C$2:$C$9,MATCH(E181,Products!$A$2:$A$9,0)))>0.005,"Price differs from list","")))
A182: LK-2064 | B182: 46225 | C182: Paul Smit | D182: Germany | E182: Oak Cutting Board | F182: =IFERROR(INDEX(Products!$B$2:$B$9,MATCH(E182,Products!$A$2:$A$9,0)),"Unknown product") -> Cookware | G182: 1 | H182: 34 | I182: =IF(OR(G182="",L182="Price differs from list"),"",G182*H182) -> 34 | J182: Card | K182: =DATE(YEAR(B182),MONTH(B182),1) -> 46204 | L182: =IF(G182="","Missing qty",IF(D182="","Missing country",IF(ABS(H182-INDEX(Products!$C$2:$C$9,MATCH(E182,Products!$A$2:$A$9,0)))>0.005,"Price differs from list","")))
A183: LK-2065 | B183: 46225 | C183: Daan Meijer | D183: Netherlands | E183: Oak Cutting Board | F183: =IFERROR(INDEX(Products!$B$2:$B$9,MATCH(E183,Products!$A$2:$A$9,0)),"Unknown product") -> Cookware | G183: 1 | H183: 34 | I183: =IF(OR(G183="",L183="Price differs from list"),"",G183*H183) -> 34 | J183: PayPal | K183: =DATE(YEAR(B183),MONTH(B183),1) -> 46204 | L183: =IF(G183="","Missing qty",IF(D183="","Missing country",IF(ABS(H183-INDEX(Products!$C$2:$C$9,MATCH(E183,Products!$A$2:$A$9,0)))>0.005,"Price differs from list","")))
A184: LK-2078 | B184: 46230 | C184: Emma Schmidt | D184: Germany | E184: Oak Cutting Board | F184: =IFERROR(INDEX(Products!$B$2:$B$9,MATCH(E184,Products!$A$2:$A$9,0)),"Unknown product") -> Cookware | G184: 1 | H184: 34 | I184: =IF(OR(G184="",L184="Price differs from list"),"",G184*H184) -> 34 | J184: PayPal | K184: =DATE(YEAR(B184),MONTH(B184),1) -> 46204 | L184: =IF(G184="","Missing qty",IF(D184="","Missing country",IF(ABS(H184-INDEX(Products!$C$2:$C$9,MATCH(E184,Products!$A$2:$A$9,0)))>0.005,"Price differs from list","")))
A185: LK-2093 | B185: 46237 | C185: Noah Müller | D185: Belgium | E185: Oak Cutting Board | F185: =IFERROR(INDEX(Products!$B$2:$B$9,MATCH(E185,Products!$A$2:$A$9,0)),"Unknown product") -> Cookware | G185: 1 | H185: 34 | I185: =IF(OR(G185="",L185="Price differs from list"),"",G185*H185) -> 34 | J185: Card | K185: =DATE(YEAR(B185),MONTH(B185),1) -> 46235 | L185: =IF(G185="","Missing qty",IF(D185="","Missing country",IF(ABS(H185-INDEX(Products!$C$2:$C$9,MATCH(E185,Products!$A$2:$A$9,0)))>0.005,"Price differs from list","")))
A186: LK-2097 | B186: 46238 | C186: Hugo Wagner | D186: Netherlands | E186: Oak Cutting Board | F186: =IFERROR(INDEX(Products!$B$2:$B$9,MATCH(E186,Products!$A$2:$A$9,0)),"Unknown product") -> Cookware | G186: 1 | H186: 34 | I186: =IF(OR(G186="",L186="Price differs from list"),"",G186*H186) -> 34 | J186: PayPal | K186: =DATE(YEAR(B186),MONTH(B186),1) -> 46235 | L186: =IF(G186="","Missing qty",IF(D186="","Missing country",IF(ABS(H186-INDEX(Products!$C$2:$C$9,MATCH(E186,Products!$A$2:$A$9,0)))>0.005,"Price differs from list","")))
A187: LK-2098 | B187: 46238 | C187: Finn de Vries | D187: Germany | E187: Oak Cutting Board | F187: =IFERROR(INDEX(Products!$B$2:$B$9,MATCH(E187,Products!$A$2:$A$9,0)),"Unknown product") -> Cookware | G187: 1 | H187: 34 | I187: =IF(OR(G187="",L187="Price differs from list"),"",G187*H187) -> 34 | J187: Card | K187: =DATE(YEAR(B187),MONTH(B187),1) -> 46235 | L187: =IF(G187="","Missing qty",IF(D187="","Missing country",IF(ABS(H187-INDEX(Products!$C$2:$C$9,MATCH(E187,Products!$A$2:$A$9,0)))>0.005,"Price differs from list","")))
A188: LK-2102 | B188: 46240 | C188: Daan Wagner | D188: Netherlands | E188: Oak Cutting Board | F188: =IFERROR(INDEX(Products!$B$2:$B$9,MATCH(E188,Products!$A$2:$A$9,0)),"Unknown product") -> Cookware | G188: 1 | H188: 34 | I188: =IF(OR(G188="",L188="Price differs from list"),"",G188*H188) -> 34 | J188: PayPal | K188: =DATE(YEAR(B188),MONTH(B188),1) -> 46235 | L188: =IF(G188="","Missing qty",IF(D188="","Missing country",IF(ABS(H188-INDEX(Products!$C$2:$C$9,MATCH(E188,Products!$A$2:$A$9,0)))>0.005,"Price differs from list","")))
... A220: LK-2278 | B220: 46307 | C220: Daan Visser | D220: France | E220: Oak Cutting Board | F220: =IFERROR(INDEX(Products!$B$2:$B$9,MATCH(E220,Products!$A$2:$A$9,0)),"Unknown product") -> Cookware | G220: 4 | H220: 34 | I220: =IF(OR(G220="",L220="Price differs from list"),"",G220*H220) -> 136 | J220: Card | K220: =DATE(YEAR(B220),MONTH(B220),1) -> 46296 | L220: =IF(G220="","Missing qty",IF(D220="","Missing country",IF(ABS(H220-INDEX(Products!$C$2:$C$9,MATCH(E220,Products!$A$2:$A$9,0)))>0.005,"Price differs from list","")))
A221: LK-2172 | B221: 46264 | C221: Finn Bos | D221: Netherlands | E221: Oak Cutting Board | F221: =IFERROR(INDEX(Products!$B$2:$B$9,MATCH(E221,Products!$A$2:$A$9,0)),"Unknown product") -> Cookware | H221: 34 | I221: =IF(OR(G221="",L221="Price differs from list"),"",G221*H221) | J221: PayPal | K221: =DATE(YEAR(B221),MONTH(B221),1) -> 46235 | L221: =IF(G221="","Missing qty",IF(D221="","Missing country",IF(ABS(H221-INDEX(Products!$C$2:$C$9,MATCH(E221,Products!$A$2:$A$9,0)))>0.005,"Price differs from list",""))) -> Missing qty
A222: LK-2038 | B222: 46214 | C222: Liam Hendriks | D222: Belgium | E222: Coffee Grinder | F222: =IFERROR(INDEX(Products!$B$2:$B$9,MATCH(E222,Products!$A$2:$A$9,0)),"Unknown product") -> Coffee | G222: 1 | H222: 39.95 | I222: =IF(OR(G222="",L222="Price differs from list"),"",G222*H222) -> 39.95 | J222: Card | K222: =DATE(YEAR(B222),MONTH(B222),1) -> 46204 | L222: =IF(G222="","Missing qty",IF(D222="","Missing country",IF(ABS(H222-INDEX(Products!$C$2:$C$9,MATCH(E222,Products!$A$2:$A$9,0)))>0.005,"Price differs from list","")))
A223: LK-2041 | B223: 46215 | C223: Paul Jansen | D223: Germany | E223: Coffee Grinder | F223: =IFERROR(INDEX(Products!$B$2:$B$9,MATCH(E223,Products!$A$2:$A$9,0)),"Unknown product") -> Coffee | G223: 1 | H223: 39.95 | I223: =IF(OR(G223="",L223="Price differs from list"),"",G223*H223) -> 39.95 | J223: iDEAL | K223: =DATE(YEAR(B223),MONTH(B223),1) -> 46204 | L223: =IF(G223="","Missing qty",IF(D223="","Missing country",IF(ABS(H223-INDEX(Products!$C$2:$C$9,MATCH(E223,Products!$A$2:$A$9,0)))>0.005,"Price differs from list","")))
A224: LK-2051 | B224: 46220 | C224: Lucas de Vries | D224: Netherlands | E224: Coffee Grinder | F224: =IFERROR(INDEX(Products!$B$2:$B$9,MATCH(E224,Products!$A$2:$A$9,0)),"Unknown product") -> Coffee | G224: 1 | H224: 39.95 | I224: =IF(OR(G224="",L224="Price differs from list"),"",G224*H224) -> 39.95 | J224: PayPal | K224: =DATE(YEAR(B224),MONTH(B224),1) -> 46204 | L224: =IF(G224="","Missing qty",IF(D224="","Missing country",IF(ABS(H224-INDEX(Products!$C$2:$C$9,MATCH(E224,Products!$A$2:$A$9,0)))>0.005,"Price differs from list","")))
A225: LK-2055 | B225: 46221 | C225: Anna Bos | D225: Netherlands | E225: Coffee Grinder | F225: =IFERROR(INDEX(Products!$B$2:$B$9,MATCH(E225,Products!$A$2:$A$9,0)),"Unknown product") -> Coffee | G225: 1 | H225: 39.95 | I225: =IF(OR(G225="",L225="Price differs from list"),"",G225*H225) -> 39.95 | J225: PayPal | K225: =DATE(YEAR(B225),MONTH(B225),1) -> 46204 | L225: =IF(G225="","Missing qty",IF(D225="","Missing country",IF(ABS(H225-INDEX(Products!$C$2:$C$9,MATCH(E225,Products!$A$2:$A$9,0)))>0.005,"Price differs from list","")))
A226: LK-2076 | B226: 46230 | C226: Lena Smit | D226: Germany | E226: Coffee Grinder | F226: =IFERROR(INDEX(Products!$B$2:$B$9,MATCH(E226,Products!$A$2:$A$9,0)),"Unknown product") -> Coffee | G226: 1 | H226: 39.95 | I226: =IF(OR(G226="",L226="Price differs from list"),"",G226*H226) -> 39.95 | J226: Card | K226: =DATE(YEAR(B226),MONTH(B226),1) -> 46204 | L226: =IF(G226="","Missing qty",IF(D226="","Missing country",IF(ABS(H226-INDEX(Products!$C$2:$C$9,MATCH(E226,Products!$A$2:$A$9,0)))>0.005,"Price differs from list","")))
A227: LK-2081 | B227: 46233 | C227: Lea de Vries | D227: Netherlands | E227: Coffee Grinder | F227: =IFERROR(INDEX(Products!$B$2:$B$9,MATCH(E227,Products!$A$2:$A$9,0)),"Unknown product") -> Coffee | G227: 1 | H227: 39.95 | I227: =IF(OR(G227="",L227="Price differs from list"),"",G227*H227) -> 39.95 | J227: iDEAL | K227: =DATE(YEAR(B227),MONTH(B227),1) -> 46204 | L227: =IF(G227="","Missing qty",IF(D227="","Missing country",IF(ABS(H227-INDEX(Products!$C$2:$C$9,MATCH(E227,Products!$A$2:$A$9,0)))>0.005,"Price differs from list","")))
A228: LK-2087 | B228: 46235 | C228: Lotte Jansen | D228: Netherlands | E228: Coffee Grinder | F228: =IFERROR(INDEX(Products!$B$2:$B$9,MATCH(E228,Products!$A$2:$A$9,0)),"Unknown product") -> Coffee | G228: 1 | H228: 39.95 | I228: =IF(OR(G228="",L228="Price differs from list"),"",G228*H228) -> 39.95 | J228: Card | K228: =DATE(YEAR(B228),MONTH(B228),1) -> 46235 | L228: =IF(G228="","Missing qty",IF(D228="","Missing country",IF(ABS(H228-INDEX(Products!$C$2:$C$9,MATCH(E228,Products!$A$2:$A$9,0)))>0.005,"Price differs from list","")))
A229: LK-2101 | B229: 46240 | C229: Mila Hendriks | D229: Netherlands | E229: Coffee Grinder | F229: =IFERROR(INDEX(Products!$B$2:$B$9,MATCH(E229,Products!$A$2:$A$9,0)),"Unknown product") -> Coffee | G229: 1 | H229: 39.95 | I229: =IF(OR(G229="",L229="Price differs from list"),"",G229*H229) -> 39.95 | J229: iDEAL | K229: =DATE(YEAR(B229),MONTH(B229),1) -> 46235 | L229: =IF(G229="","Missing qty",IF(D229="","Missing country",IF(ABS(H229-INDEX(Products!$C$2:$C$9,MATCH(E229,Products!$A$2:$A$9,0)))>0.005,"Price differs from list","")))
A230: LK-2107 | B230: 46242 | C230: Lea de Vries | D230: Netherlands | E230: Coffee Grinder | F230: =IFERROR(INDEX(Products!$B$2:$B$9,MATCH(E230,Products!$A$2:$A$9,0)),"Unknown product") -> Coffee | G230: 1 | H230: 39.95 | I230: =IF(OR(G230="",L230="Price differs from list"),"",G230*H230) -> 39.95 | J230: Card | K230: =DATE(YEAR(B230),MONTH(B230),1) -> 46235 | L230: =IF(G230="","Missing qty",IF(D230="","Missing country",IF(ABS(H230-INDEX(Products!$C$2:$C$9,MATCH(E230,Products!$A$2:$A$9,0)))>0.005,"Price differs from list","")))
A231: LK-2123 | B231: 46248 | C231: Marie Bos | D231: Netherlands | E231: Coffee Grinder | F231: =IFERROR(INDEX(Products!$B$2:$B$9,MATCH(E231,Products!$A$2:$A$9,0)),"Unknown product") -> Coffee | G231: 1 | H231: 39.95 | I231: =IF(OR(G231="",L231="Price differs from list"),"",G231*H231) -> 39.95 | J231: PayPal | K231: =DATE(YEAR(B231),MONTH(B231),1) -> 46235 | L231: =IF(G231="","Missing qty",IF(D231="","Missing country",IF(ABS(H231-INDEX(Products!$C$2:$C$9,MATCH(E231,Products!$A$2:$A$9,0)))>0.005,"Price differs from list","")))
A232: LK-2165 | B232: 46262 | C232: Nora Bakker | E232: Coffee Grinder | F232: =IFERROR(INDEX(Products!$B$2:$B$9,MATCH(E232,Products!$A$2:$A$9,0)),"Unknown product") -> Coffee | G232: 1 | H232: 39.95 | I232: =IF(OR(G232="",L232="Price differs from list"),"",G232*H232) -> 39.95 | J232: iDEAL | K232: =DATE(YEAR(B232),MONTH(B232),1) -> 46235 | L232: =IF(G232="","Missing qty",IF(D232="","Missing country",IF(ABS(H232-INDEX(Products!$C$2:$C$9,MATCH(E232,Products!$A$2:$A$9,0)))>0.005,"Price differs from list",""))) -> Missing country
A233: LK-2168 | B233: 46263 | C233: Marie Peters | D233: Netherlands | E233: Coffee Grinder | F233: =IFERROR(INDEX(Products!$B$2:$B$9,MATCH(E233,Products!$A$2:$A$9,0)),"Unknown product") -> Coffee | G233: 1 | H233: 39.95 | I233: =IF(OR(G233="",L233="Price differs from list"),"",G233*H233) -> 39.95 | J233: iDEAL | K233: =DATE(YEAR(B233),MONTH(B233),1) -> 46235 | L233: =IF(G233="","Missing qty",IF(D233="","Missing country",IF(ABS(H233-INDEX(Products!$C$2:$C$9,MATCH(E233,Products!$A$2:$A$9,0)))>0.005,"Price differs from list","")))
A234: LK-2173 | B234: 46264 | C234: Marie Bos | D234: Netherlands | E234: Coffee Grinder | F234: =IFERROR(INDEX(Products!$B$2:$B$9,MATCH(E234,Products!$A$2:$A$9,0)),"Unknown product") -> Coffee | G234: 1 | H234: 39.95 | I234: =IF(OR(G234="",L234="Price differs from list"),"",G234*H234) -> 39.95 | J234: Card | K234: =DATE(YEAR(B234),MONTH(B234),1) -> 46235 | L234: =IF(G234="","Missing qty",IF(D234="","Missing country",IF(ABS(H234-INDEX(Products!$C$2:$C$9,MATCH(E234,Products!$A$2:$A$9,0)))>0.005,"Price differs from list","")))
A235: LK-2177 | B235: 46265 | C235: Mila Wagner | D235: Netherlands | E235: Coffee Grinder | F235: =IFERROR(INDEX(Products!$B$2:$B$9,MATCH(E235,Products!$A$2:$A$9,0)),"Unknown product") -> Coffee | G235: 1 | H235: 39.95 | I235: =IF(OR(G235="",L235="Price differs from list"),"",G235*H235) -> 39.95 | J235: Card | K235: =DATE(YEAR(B235),MONTH(B235),1) -> 46235 | L235: =IF(G235="","Missing qty",IF(D235="","Missing country",IF(ABS(H235-INDEX(Products!$C$2:$C$9,MATCH(E235,Products!$A$2:$A$9,0)))>0.005,"Price differs from list","")))
A236: LK-2188 | B236: 46269 | C236: Sara Vos | D236: France | E236: Coffee Grinder | F236: =IFERROR(INDEX(Products!$B$2:$B$9,MATCH(E236,Products!$A$2:$A$9,0)),"Unknown product") -> Coffee | G236: 1 | H236: 39.95 | I236: =IF(OR(G236="",L236="Price differs from list"),"",G236*H236) -> 39.95 | J236: PayPal | K236: =DATE(YEAR(B236),MONTH(B236),1) -> 46266 | L236: =IF(G236="","Missing qty",IF(D236="","Missing country",IF(ABS(H236-INDEX(Products!$C$2:$C$9,MATCH(E236,Products!$A$2:$A$9,0)))>0.005,"Price differs from list","")))
A237: LK-2194 | B237: 46271 | C237: Sophie Visser | D237: Netherlands | E237: Coffee Grinder | F237: =IFERROR(INDEX(Products!$B$2:$B$9,MATCH(E237,Products!$A$2:$A$9,0)),"Unknown product") -> Coffee | G237: 1 | H237: 39.95 | I237: =IF(OR(G237="",L237="Price differs from list"),"",G237*H237) -> 39.95 | J237: iDEAL | K237: =DATE(YEAR(B237),MONTH(B237),1) -> 46266 | L237: =IF(G237="","Missing qty",IF(D237="","Missing country",IF(ABS(H237-INDEX(Products!$C$2:$C$9,MATCH(E237,Products!$A$2:$A$9,0)))>0.005,"Price differs from list","")))
A238: LK-2223 | B238: 46283 | C238: Claire Jansen | D238: Netherlands | E238: Coffee Grinder | F238: =IFERROR(INDEX(Products!$B$2:$B$9,MATCH(E238,Products!$A$2:$A$9,0)),"Unknown product") -> Coffee | G238: 1 | H238: 39.95 | I238: =IF(OR(G238="",L238="Price differs from list"),"",G238*H238) -> 39.95 | J238: PayPal | K238: =DATE(YEAR(B238),MONTH(B238),1) -> 46266 | L238: =IF(G238="","Missing qty",IF(D238="","Missing country",IF(ABS(H238-INDEX(Products!$C$2:$C$9,MATCH(E238,Products!$A$2:$A$9,0)))>0.005,"Price differs from list","")))
A239: LK-2227 | B239: 46284 | C239: Liam Jansen | D239: Germany | E239: Coffee Grinder | F239: =IFERROR(INDEX(Products!$B$2:$B$9,MATCH(E239,Products!$A$2:$A$9,0)),"Unknown product") -> Coffee | G239: 1 | H239: 39.95 | I239: =IF(OR(G239="",L239="Price differs from list"),"",G239*H239) -> 39.95 | J239: PayPal | K239: =DATE(YEAR(B239),MONTH(B239),1) -> 46266 | L239: =IF(G239="","Missing qty",IF(D239="","Missing country",IF(ABS(H239-INDEX(Products!$C$2:$C$9,MATCH(E239,Products!$A$2:$A$9,0)))>0.005,"Price differs from list","")))
A240: LK-2233 | B240: 46287 | C240: Julia Bakker | D240: Netherlands | E240: Coffee Grinder | F240: =IFERROR(INDEX(Products!$B$2:$B$9,MATCH(E240,Products!$A$2:$A$9,0)),"Unknown product") -> Coffee | G240: 1 | H240: 39.95 | I240: =IF(OR(G240="",L240="Price differs from list"),"",G240*H240) -> 39.95 | J240: iDEAL | K240: =DATE(YEAR(B240),MONTH(B240),1) -> 46266 | L240: =IF(G240="","Missing qty",IF(D240="","Missing country",IF(ABS(H240-INDEX(Products!$C$2:$C$9,MATCH(E240,Products!$A$2:$A$9,0)))>0.005,"Price differs from list","")))
A241: LK-2244 | B241: 46293 | C241: Emma Meijer | D241: Netherlands | E241: Coffee Grinder | F241: =IFERROR(INDEX(Products!$B$2:$B$9,MATCH(E241,Products!$A$2:$A$9,0)),"Unknown product") -> Coffee | G241: 1 | H241: 39.95 | I241: =IF(OR(G241="",L241="Price differs from list"),"",G241*H241) -> 39.95 | J241: iDEAL | K241: =DATE(YEAR(B241),MONTH(B241),1) -> 46266 | L241: =IF(G241="","Missing qty",IF(D241="","Missing country",IF(ABS(H241-INDEX(Products!$C$2:$C$9,MATCH(E241,Products!$A$2:$A$9,0)))>0.005,"Price differs from list","")))
A242: LK-2271 | B242: 46304 | C242: Claire Bakker | D242: Netherlands | E242: Coffee Grinder | F242: =IFERROR(INDEX(Products!$B$2:$B$9,MATCH(E242,Products!$A$2:$A$9,0)),"Unknown product") -> Coffee | G242: 1 | H242: 39.95 | I242: =IF(OR(G242="",L242="Price differs from list"),"",G242*H242) -> 39.95 | J242: Card | K242: =DATE(YEAR(B242),MONTH(B242),1) -> 46296 | L242: =IF(G242="","Missing qty",IF(D242="","Missing country",IF(ABS(H242-INDEX(Products!$C$2:$C$9,MATCH(E242,Products!$A$2:$A$9,0)))>0.005,"Price differs from list","")))
A243: LK-2279 | B243: 46307 | C243: Eva Maes | D243: Belgium | E243: Coffee Grinder | F243: =IFERROR(INDEX(Products!$B$2:$B$9,MATCH(E243,Products!$A$2:$A$9,0)),"Unknown product") -> Coffee | G243: 1 | H243: 39.95 | I243: =IF(OR(G243="",L243="Price differs from list"),"",G243*H243) -> 39.95 | J243: iDEAL | K243: =DATE(YEAR(B243),MONTH(B243),1) -> 46296 | L243: =IF(G243="","Missing qty",IF(D243="","Missing country",IF(ABS(H243-INDEX(Products!$C$2:$C$9,MATCH(E243,Products!$A$2:$A$9,0)))>0.005,"Price differs from list","")))
A244: LK-2281 | B244: 46308 | C244: Claire Schmidt | D244: France | E244: Coffee Grinder | F244: =IFERROR(INDEX(Products!$B$2:$B$9,MATCH(E244,Products!$A$2:$A$9,0)),"Unknown product") -> Coffee | G244: 1 | H244: 39.95 | I244: =IF(OR(G244="",L244="Price differs from list"),"",G244*H244) -> 39.95 | J244: PayPal | K244: =DATE(YEAR(B244),MONTH(B244),1) -> 46296 | L244: =IF(G244="","Missing qty",IF(D244="","Missing country",IF(ABS(H244-INDEX(Products!$C$2:$C$9,MATCH(E244,Products!$A$2:$A$9,0)))>0.005,"Price differs from list","")))
... A267: LK-2282 | B267: 46309 | C267: Paul Bos | D267: Germany | E267: Cast Iron Pan 26cm | F267: =IFERROR(INDEX(Products!$B$2:$B$9,MATCH(E267,Products!$A$2:$A$9,0)),"Unknown product") -> Cookware | G267: 2 | H267: 44.95 | I267: =IF(OR(G267="",L267="Price differs from list"),"",G267*H267) -> 89.9 | J267: iDEAL | K267: =DATE(YEAR(B267),MONTH(B267),1) -> 46296 | L267: =IF(G267="","Missing qty",IF(D267="","Missing country",IF(ABS(H267-INDEX(Products!$C$2:$C$9,MATCH(E267,Products!$A$2:$A$9,0)))>0.005,"Price differs from list","")))
A268: LK-2056 | B268: 46222 | C268: Paul Bakker | E268: Cast Iron Pan 26cm | F268: =IFERROR(INDEX(Products!$B$2:$B$9,MATCH(E268,Products!$A$2:$A$9,0)),"Unknown product") -> Cookware | G268: 3 | H268: 44.95 | I268: =IF(OR(G268="",L268="Price differs from list"),"",G268*H268) -> 134.85 | J268: Card | K268: =DATE(YEAR(B268),MONTH(B268),1) -> 46204 | L268: =IF(G268="","Missing qty",IF(D268="","Missing country",IF(ABS(H268-INDEX(Products!$C$2:$C$9,MATCH(E268,Products!$A$2:$A$9,0)))>0.005,"Price differs from list",""))) -> Missing country
A269: LK-2195 | B269: 46271 | C269: Lucas Mulder | D269: France | E269: Cast Iron Pan 26cm | F269: =IFERROR(INDEX(Products!$B$2:$B$9,MATCH(E269,Products!$A$2:$A$9,0)),"Unknown product") -> Cookware | G269: 3 | H269: 44.95 | I269: =IF(OR(G269="",L269="Price differs from list"),"",G269*H269) -> 134.85 | J269: Card | K269: =DATE(YEAR(B269),MONTH(B269),1) -> 46266 | L269: =IF(G269="","Missing qty",IF(D269="","Missing country",IF(ABS(H269-INDEX(Products!$C$2:$C$9,MATCH(E269,Products!$A$2:$A$9,0)))>0.005,"Price differs from list","")))
A270: LK-2083 | B270: 46233 | C270: Levi Hendriks | D270: Netherlands | E270: Cast Iron Pan 26cm | F270: =IFERROR(INDEX(Products!$B$2:$B$9,MATCH(E270,Products!$A$2:$A$9,0)),"Unknown product") -> Cookware | G270: 4 | H270: 44.95 | I270: =IF(OR(G270="",L270="Price differs from list"),"",G270*H270) -> 179.8 | J270: PayPal | K270: =DATE(YEAR(B270),MONTH(B270),1) -> 46204 | L270: =IF(G270="","Missing qty",IF(D270="","Missing country",IF(ABS(H270-INDEX(Products!$C$2:$C$9,MATCH(E270,Products!$A$2:$A$9,0)))>0.005,"Price differs from list","")))
A271: LK-2099 | B271: 46239 | C271: Daan Smit | D271: Germany | E271: Cast Iron Pan 26cm | F271: =IFERROR(INDEX(Products!$B$2:$B$9,MATCH(E271,Products!$A$2:$A$9,0)),"Unknown product") -> Cookware | G271: 4 | H271: 44.95 | I271: =IF(OR(G271="",L271="Price differs from list"),"",G271*H271) -> 179.8 | J271: Card | K271: =DATE(YEAR(B271),MONTH(B271),1) -> 46235 | L271: =IF(G271="","Missing qty",IF(D271="","Missing country",IF(ABS(H271-INDEX(Products!$C$2:$C$9,MATCH(E271,Products!$A$2:$A$9,0)))>0.005,"Price differs from list","")))
A272: LK-2002 | B272: 46204 | C272: Lena Müller | D272: Netherlands | E272: Pour-Over Kettle | F272: =IFERROR(INDEX(Products!$B$2:$B$9,MATCH(E272,Products!$A$2:$A$9,0)),"Unknown product") -> Coffee | G272: 1 | H272: 49 | I272: =IF(OR(G272="",L272="Price differs from list"),"",G272*H272) -> 49 | J272: Card | K272: =DATE(YEAR(B272),MONTH(B272),1) -> 46204 | L272: =IF(G272="","Missing qty",IF(D272="","Missing country",IF(ABS(H272-INDEX(Products!$C$2:$C$9,MATCH(E272,Products!$A$2:$A$9,0)))>0.005,"Price differs from list","")))
A273: LK-2003 | B273: 46204 | C273: Paul Dubois | D273: Belgium | E273: Pour-Over Kettle | F273: =IFERROR(INDEX(Products!$B$2:$B$9,MATCH(E273,Products!$A$2:$A$9,0)),"Unknown product") -> Coffee | G273: 1 | H273: 49 | I273: =IF(OR(G273="",L273="Price differs from list"),"",G273*H273) -> 49 | J273: Card | K273: =DATE(YEAR(B273),MONTH(B273),1) -> 46204 | L273: =IF(G273="","Missing qty",IF(D273="","Missing country",IF(ABS(H273-INDEX(Products!$C$2:$C$9,MATCH(E273,Products!$A$2:$A$9,0)))>0.005,"Price differs from list","")))
A274: LK-2063 | B274: 46224 | C274: Mila Jansen | D274: Netherlands | E274: Pour-Over Kettle | F274: =IFERROR(INDEX(Products!$B$2:$B$9,MATCH(E274,Products!$A$2:$A$9,0)),"Unknown product") -> Coffee | G274: 1 | H274: 49 | I274: =IF(OR(G274="",L274="Price differs from list"),"",G274*H274) -> 49 | J274: iDEAL | K274: =DATE(YEAR(B274),MONTH(B274),1) -> 46204 | L274: =IF(G274="","Missing qty",IF(D274="","Missing country",IF(ABS(H274-INDEX(Products!$C$2:$C$9,MATCH(E274,Products!$A$2:$A$9,0)))>0.005,"Price differs from list","")))
A275: LK-2096 | B275: 46238 | C275: Marie Wagner | D275: Netherlands | E275: Pour-Over Kettle | F275: =IFERROR(INDEX(Products!$B$2:$B$9,MATCH(E275,Products!$A$2:$A$9,0)),"Unknown product") -> Coffee | G275: 1 | H275: 49 | I275: =IF(OR(G275="",L275="Price differs from list"),"",G275*H275) -> 49 | J275: Card | K275: =DATE(YEAR(B275),MONTH(B275),1) -> 46235 | L275: =IF(G275="","Missing qty",IF(D275="","Missing country",IF(ABS(H275-INDEX(Products!$C$2:$C$9,MATCH(E275,Products!$A$2:$A$9,0)))>0.005,"Price differs from list","")))
A276: LK-2104 | B276: 46240 | C276: Finn Müller | D276: Germany | E276: Pour-Over Kettle | F276: =IFERROR(INDEX(Products!$B$2:$B$9,MATCH(E276,Products!$A$2:$A$9,0)),"Unknown product") -> Coffee | G276: 1 | H276: 49 | I276: =IF(OR(G276="",L276="Price differs from list"),"",G276*H276) -> 49 | J276: PayPal | K276: =DATE(YEAR(B276),MONTH(B276),1) -> 46235 | L276: =IF(G276="","Missing qty",IF(D276="","Missing country",IF(ABS(H276-INDEX(Products!$C$2:$C$9,MATCH(E276,Products!$A$2:$A$9,0)))>0.005,"Price differs from list","")))
A277: LK-2118 | B277: 46247 | C277: Anna Vos | D277: Netherlands | E277: Pour-Over Kettle | F277: =IFERROR(INDEX(Products!$B$2:$B$9,MATCH(E277,Products!$A$2:$A$9,0)),"Unknown product") -> Coffee | G277: 1 | H277: 49 | I277: =IF(OR(G277="",L277="Price differs from list"),"",G277*H277) -> 49 | J277: PayPal | K277: =DATE(YEAR(B277),MONTH(B277),1) -> 46235 | L277: =IF(G277="","Missing qty",IF(D277="","Missing country",IF(ABS(H277-INDEX(Products!$C$2:$C$9,MATCH(E277,Products!$A$2:$A$9,0)))>0.005,"Price differs from list","")))
A278: LK-2136 | B278: 46252 | C278: Hugo Müller | D278: Netherlands | E278: Pour-Over Kettle | F278: =IFERROR(INDEX(Products!$B$2:$B$9,MATCH(E278,Products!$A$2:$A$9,0)),"Unknown product") -> Coffee | G278: 1 | H278: 49 | I278: =IF(OR(G278="",L278="Price differs from list"),"",G278*H278) -> 49 | J278: PayPal | K278: =DATE(YEAR(B278),MONTH(B278),1) -> 46235 | L278: =IF(G278="","Missing qty",IF(D278="","Missing country",IF(ABS(H278-INDEX(Products!$C$2:$C$9,MATCH(E278,Products!$A$2:$A$9,0)))>0.005,"Price differs from list","")))
A279: LK-2141 | B279: 46254 | C279: Mila Bakker | D279: Netherlands | E279: Pour-Over Kettle | F279: =IFERROR(INDEX(Products!$B$2:$B$9,MATCH(E279,Products!$A$2:$A$9,0)),"Unknown product") -> Coffee | G279: 1 | H279: 49 | I279: =IF(OR(G279="",L279="Price differs from list"),"",G279*H279) -> 49 | J279: PayPal | K279: =DATE(YEAR(B279),MONTH(B279),1) -> 46235 | L279: =IF(G279="","Missing qty",IF(D279="","Missing country",IF(ABS(H279-INDEX(Products!$C$2:$C$9,MATCH(E279,Products!$A$2:$A$9,0)))>0.005,"Price differs from list","")))
A280: LK-2191 | B280: 46269 | C280: Liam de Vries | D280: Netherlands | E280: Pour-Over Kettle | F280: =IFERROR(INDEX(Products!$B$2:$B$9,MATCH(E280,Products!$A$2:$A$9,0)),"Unknown product") -> Coffee | G280: 1 | H280: 49 | I280: =IF(OR(G280="",L280="Price differs from list"),"",G280*H280) -> 49 | J280: iDEAL | K280: =DATE(YEAR(B280),MONTH(B280),1) -> 46266 | L280: =IF(G280="","Missing qty",IF(D280="","Missing country",IF(ABS(H280-INDEX(Products!$C$2:$C$9,MATCH(E280,Products!$A$2:$A$9,0)))>0.005,"Price differs from list","")))
... A301: LK-2254 | B301: 46299 | C301: Marie Mulder | D301: Netherlands | E301: Cast Iron Pan 26cm | F301: =IFERROR(INDEX(Products!$B$2:$B$9,MATCH(E301,Products!$A$2:$A$9,0)),"Unknown product") -> Cookware | G301: 1 | H301: 4495 | I301: =IF(OR(G301="",L301="Price differs from list"),"",G301*H301) | J301: Card | K301: =DATE(YEAR(B301),MONTH(B301),1) -> 46296 | L301: =IF(G301="","Missing qty",IF(D301="","Missing country",IF(ABS(H301-INDEX(Products!$C$2:$C$9,MATCH(E301,Products!$A$2:$A$9,0)))>0.005,"Price differs from list",""))) -> Price differs from list

Sheet Products
A1: Product | B1: Category | C1: List Price | E1: Blue = input. The Clean Data tab looks up category and list price here.
A2: French Press 1L | B2: Coffee | C2: 29.95
A3: Ceramic Mug Set (4) | B3: Tableware | C3: 24.95
A4: Pour-Over Kettle | B4: Coffee | C4: 49
A5: Coffee Grinder | B5: Coffee | C5: 39.95
A6: Glass Teapot | B6: Tea | C6: 27.5
A7: Cast Iron Pan 26cm | B7: Cookware | C7: 44.95
A8: Linen Tea Towels (2) | B8: Textiles | C8: 12.95
A9: Oak Cutting Board | B9: Cookware | C9: 34

Sheet Cleaning Log
A1: Cleaning log
A4: Problem found | B4: What I did | C4: Rows
A5: Empty rows in the export | B5: Removed | C5: 4
A6: Duplicate orders (exact copies and copies with different spacing/case) | B6: Kept the first, removed the rest | C6: 18
A7: Order IDs with extra spaces | B7: Trimmed | C7: 24
A8: Dates stored as text in 5 different formats | B8: Converted to real dates (read as day/month/year, European shop) | C8: 193
A9: Customer names in caps, lowercase or with extra spaces | B9: Fixed capitalization and spacing ("de", "van" kept lowercase) | C9: 109
A10: Countries written 17 different ways (NL, Holland, Deutschland...) | B10: Standardized to 4 country names | C10: 240
A11: Product names written 28 different ways | B11: Matched to the 8 products on the price list | C11: 201
A12: Quantities stored as text ("2 pcs", " 3") | B12: Converted to numbers | C12: 55
A13: Prices stored as text (€24,95 / EUR 24.95 / 24,95 €) | B13: Converted to numbers | C13: 173
A14: Payment methods written different ways | B14: Standardized to Card, PayPal, iDEAL | C14: 231
A15: Missing quantity | B15: Kept and flagged red, needs checking with the shop | C15: 3
A16: Missing country | B16: Kept and flagged red | C16: 4
A17: Price far from the price list (decimal point missing) | B17: Kept as entered, flagged red and left out of revenue until checked | C17: 3
A19: Added so it stays clean:
A20: • Dropdowns for Country, Product and Payment, and a whole-number rule for Qty
A21: • Category and Total calculated by formula, never typed
A22: • Check column flags missing or suspicious values, flagged rows turn red
A23: • Summary tab updates automatically when data changes

Sheet Original Data
A1: order id | B1: Date | C1: customer name | D1: COUNTRY | E1: Product | F1: qty | G1: Price | H1: payment method | J1: Untouched copy of the original export, kept for comparison.
A2: LK-2001 | B2: 46204 | C2: Eva Dubois | D2: france | E2: french press 1l | F2: 3 | G2: 29,95 € | H2: Card
A3: LK-2002 | B3: 46204 | C3: Lena Müller | D3: netherlands | E3: Pour over kettle | F3: 1 | G3: 49 | H3: CARD
A4: LK-2003 | B4: 46204 | C4: paul dubois | D4: België | E4: Pour over kettle | F4: 1 | G4: 49 | H4: CARD
A5: LK-2004 | B5: 2026-07-02 | C5: julia jansen | D5: france | E5: Ceramic mug set x4 | F5: 1 | G5: €24,95 | H5: Credit card
A6: LK-2005 | B6: 02/07/2026 | C6: Daan Martin | D6: NL | E6: coffee grinder | F6: 4 | G6: 39.95 | H6: Card
A7: LK-2006 | B7: 02.07.2026 | C7: PAUL SMIT | D7: netherlands | E7: Oak Cutting Board | F7: 1 | G7: EUR 34.00 | H7: card
A8: LK-2007 | B8: 46205 | C8: Paul Hendriks | D8: germany | E8: Pour-Over Kettle | F8: 2 | G8: 49 | H8: CARD
A9: LK-2008 | B9: 02.07.2026 | C9: Lotte Hendriks | D9: Germany | E9: FRENCH PRESS 1L | F9: 3 | G9: €29,95 | H9: Paypal
A10: LK-2009 | B10: 46206 | C10: daan maes | D10: Deutschland | E10: Ceramic Mug Set (4) | F10: 3 | G10: 24.95 | H10: Card
A11: LK-2010 | B11: July 3, 2026 | C11: Noah Wagner | D11: France | E11: Glass Teapot | F11: 2 | G11: 27.5 | H11: CARD
A12: LK-2011 | B12: 03.07.2026 | C12: Lena Wagner | D12: France | E12: pour-over kettle | F12: 2 pcs | G12: 49.00 | H12: Credit card
A13: LK-2004 | B13: 2026-07-02 | C13: julia jansen | D13: france | E13: Ceramic mug set x4 | F13: 1 | G13: €24,95 | H13: Credit card
A14: LK-2012 | B14: 46207 | C14: max dubois | D14: NL | E14: Linen Tea Towels (2) | F14: 1 | G14: 12.95 | H14: ideal
A15: LK-2013 | B15: 46207 | C15: Marie Jansen | D15: Germany | E15: French Press 1L | F15: 2 | G15: EUR 29.95 | H15: PayPal
A16: LK-2014 | B16: 4 Jul 2026 | C16: Jonas Mulder | D16: Holland | E16: Pour over kettle | F16: 2 | G16: 49 | H16: iDEAL
A17: LK-2015 | B17: 46208 | C17: Eva Meijer | D17: belgium | E17: Ceramic mug set x4 | F17: 2 | G17: 24.95 | H17: ideal
A18: LK-2016 | B18: 46208 | C18: Paul Hendriks | D18: belgium | E18: FRENCH PRESS 1L | F18: 2 | G18: 29,95 € | H18: Paypal
A19: LK-2017 | B19: 2026-07-05 | C19: sophie peeters | D19: Nederland | E19: Coffee Grinder | F19: 3 | G19: 39.95 | H19: IDEAL
A20: LK-2016 | B20: 46208 | C20: Paul Hendriks | D20: belgium | E20: FRENCH PRESS 1L | F20: 2 | G20: 29,95 € | H20: Paypal
A21: LK-2018 | B21: 46209 | C21: Claire Peters | D21: belgium | E21: Oak Chopping Board | F21: 1 pcs | G21: 34.00 | H21: paypal
A22: LK-2019 | B22: 46209 | C22: Lotte Dubois | D22: Netherlands | E22: linen tea towels | F22: 2 | G22: €12,95 | H22: iDEAL
A23: LK-2020 | B23: 2026-07-07 | C23: Sem Meijer | D23: germany | E23: Linen Tea Towels (2) | F23: 1 | G23: 12.95 | H23: PayPal
A24: LK-2021 | B24: 2026-07-07 | C24: Emma Dubois | D24: germany | E24: Glass Tea Pot | F24: 2 | G24: 27.50 | H24: Card
A25: LK-2022 | B25: 07/07/2026 | C25: Anna Visser | D25: Netherlands | E25: Cast-Iron Pan 26cm | F25: 1 | G25: €44,95 | H25: iDEAL
A26: LK-2023 | B26: 46210 | C26: Anna Müller | D26: Holland | E26: Cast Iron Pan 26cm | F26: 1 | G26: 44.95 | H26: paypal
A27: LK-2024 | B27: 46210 | C27: Daan Maes | D27: Nederland | E27: French Press 1 L | F27: 1 | G27: €29,95 | H27: PayPal
A28: LK-2025 | B28: 2026-07-07 | C28: Sophie Hendriks | D28: germany | E28: pour-over kettle | F28: 2 | G28: EUR 49.00 | H28: CARD
A29: LK-2026 | B29: 08/07/2026 | C29: Eva Hendriks | D29: germany | E29: Cast Iron Pan 26cm | F29: 1 | G29: 44.95 | H29: Paypal
A30: LK-2027 | B30: 2026-07-08 | C30: emma bakker | D30: Belgium | E30: Linen Tea Towels (2) | F30: 1 | G30: 12.95 | H30: Credit card
A31: LK-2028 | B31: 2026-07-08 | C31: Finn Bos | D31: BE | E31: french press 1l | F31: 2 | G31: 29.95 | H31: paypal
A32: LK-2029 | B32: July 8, 2026 | C32: Mila Smit | D32: Germany | E32: Oak Cutting Board | F32: 1 | G32: EUR 34.00 | H32: paypal
A33: LK-2030 | B33: 46212 | C33: Sem Visser | D33: Holland | E33: glass teapot | F33: 1 | G33: 27.5 | H33: card
A34: LK-2031 | B34: 09/07/2026 | C34: Jonas Bakker | D34: Holland | E34: linen tea towels | F34: 2 | G34: 12.95 | H34: ideal
A35: LK-2024 | B35: 46210 | C35: Daan Maes | D35: Nederland | E35: French Press 1 L | F35: 1 | G35: €29,95 | H35: PayPal
A36: LK-2032 | B36: 09.07.2026 | C36: julia martin | D36: Germany | E36: FRENCH PRESS 1L | F36: 1 | G36: EUR 29.95 | H36: ideal
A37: LK-2033 | B37: 46213 | C37: Hugo Dubois | D37: Nederland | E37: Ceramic Mug Set (4) | F37: 1 | G37: 24.95 | H37: Paypal
A38: LK-2034 | B38: 11.07.2026 | C38: Sem Vos | D38: Nederland | E38: French Press 1L | F38: 1 | G38: €29,95 | H38: Credit card
A39: LK-2035 | B39: 2026-07-11 | C39: Lena Meijer | D39: Nederland | E39: FRENCH PRESS 1L | F39: 1 | G39: 29.95 | H39: Paypal
A40: LK-2036 | B40: 2026-07-11 | C40: Eva Vos | D40: NL | E40: French Press 1 L | F40: 1 pcs | G40: €29,95 | H40: Credit card
A41: LK-2037 | B41: 46214 | C41: Eva Peters | D41: netherlands | E41: Oak Chopping Board | F41: 1 pcs | G41: 34.00 | H41: ideal
A42: LK-2038 | B42: 11.07.2026 | C42: Liam Hendriks | D42: Belgium | E42: Coffee Grinder | F42: 1 | G42: 39.95 | H42: CARD
A43: LK-2039 | B43: 11 Jul 2026 | C43: Marie Dubois | D43: Holland | E43: Oak Chopping Board | F43: 1 pcs | G43: EUR 34.00 | H43: iDeal
A44: LK-2040 | B44: 2026-07-11 | C44: Julia de Vries | D44: netherlands | E44: FRENCH PRESS 1L | F44: 1 | G44: EUR 29.95 | H44: ideal
A45: LK-2041 | B45: 2026-07-12 | C45: Paul Jansen | D45: DE | E45: coffee grinder | F45: 1 | G45: €39,95 | H45: iDeal
A47: LK-2042 | B47: 12.07.2026 | C47: Sophie Meijer | D47: Netherlands | E47: Linen Tea Towel x2 | F47: 4 | G47: 12.95 | H47: paypal
A48: LK-2043 | B48: July 12, 2026 | C48: claire hendriks | D48: Nederland | E48: Glass Teapot | F48: 1 | G48: 27.50 | H48: IDEAL
A49: LK-2044 | B49: July 12, 2026 | C49: Daan Peeters | D49: belgium | E49: Oak Chopping Board | F49: 2 | G49: 34 | H49: card
A50: LK-2045 | B50: 46217 | C50: Noah Vos | D50: Netherlands | E50: French Press 1L | F50: 1 | G50: 29.95 | H50: iDEAL
A51: LK-2046 | B51: 46218 | C51: Sara Peters | D51: france | E51: Oak Chopping Board | F51: 2 | G51: 34.00 | H51: Credit card
A52: LK-2047 | B52: 15/07/2026 | C52: JONAS VISSER | D52: NL | E52: Oak Cutting Board | F52: 2 | G52: €34,00 | H52: IDEAL
A53: LK-2048 | B53: 16.07.2026 | C53: Sophie Müller | D53: BE | E53: french press 1l | F53: 2 | G53: 29.95 | H53: card
A54: LK-2049 | B54: 2026-07-16 | C54: Sophie Wagner | D54: Netherlands | E54: Cast Iron Pan 26cm | F54: 1 | G54: €44,95 | H54: Credit card
A55: LK-2050 | B55: 17 Jul 2026 | C55: Marie Smit | D55: Germany | E55: French Press 1 L | F55: 2 | G55: 29.95 | H55: CARD
A56: LK-2051 | B56: 46220 | C56: Lucas de Vries | D56: Nederland | E56: Coffee Grinder | F56: 1 | G56: €39,95 | H56: paypal
A57: LK-2052 | B57: 46220 | C57: Lena Martin | D57: Belgium | E57: FRENCH PRESS 1L | F57: 2 | G57: 29.95 | H57: card
A58: LK-2053 | B58: July 17, 2026 | C58: Noah Bakker | D58: netherlands | E58: Glass Teapot | F58: 1 pcs | G58: 27,50 € | H58: IDEAL
A59: LK-2054 | B59: 46220 | C59: Lea Peeters | D59: Belgium | E59: Linen Tea Towels (2) | F59: 1 | G59: EUR 12.95 | H59: card
A60: LK-2055 | B60: 2026-07-18 | C60: ANNA BOS | D60: Netherlands | E60: coffee grinder | F60: 1 | G60: 39.95 | H60: paypal
A61: LK-2056 | B61: July 19, 2026 | C61: Paul Bakker | E61: Cast-Iron Pan 26cm | F61: 3 | G61: 44.95 | H61: Credit card
A62: LK-2057 | B62: 19/07/2026 | C62: Noah Peeters | D62: Holland | E62: Ceramic mug set x4 | F62: 1 | G62: 24.95 | H62: iDeal
A63: LK-2058 | B63: 46222 | C63: Lea Wagner | D63: Netherlands | E63: Ceramic Mug Set (4) | F63: 4 | G63: 24.95 | H63: Paypal
A64: LK-2059 | B64: 46222 | C64: Julia de Vries | D64: DE | E64: FRENCH PRESS 1L | F64: 1 | G64: 29,95 € | H64: card
A65: LK-2060 | B65: 2026-07-19 | C65: LENA DUBOIS | D65: Holland | E65: ceramic mug set (4) | F65: 1 | G65: 2495 | H65: iDeal
A66: LK-2061 | B66: 46223 | C66: Noah Martin | D66: DE | E66: Glass Tea Pot | F66: 4 | G66: €27,50 | H66: Credit card
A67: LK-2062 | B67: 2026-07-20 | C67: Hugo Wagner | D67: Nederland | E67: ceramic mug set (4) | F67: 2 | G67: 24,95 € | H67: iDEAL
A68: LK-2048 | B68: 16.07.2026 | C68: Sophie Müller | D68: BE | E68: french press 1l | F68: 2 | G68: 29.95 | H68: card
A69: LK-2063 | B69: 46224 | C69: mila jansen | D69: Holland | E69: Pour-Over Kettle | F69: 1 | G69: €49,00 | H69: IDEAL
A70: LK-2064 | B70: 22/07/2026 | C70: PAUL SMIT | D70: DE | E70: oak cutting board | F70: 1 | G70: 34.00 | H70: Card
A71: LK-2065 | B71: 2026-07-22 | C71: Daan Meijer | D71: netherlands | E71: Oak Cutting Board | F71: 1 | G71: 34 | H71: PayPal
A72: LK-2066 | B72: 22 Jul 2026 | C72: Jonas Jansen | D72: netherlands | E72: Pourover Kettle | F72: 3 pcs | G72: €49,00 | H72: Paypal
A74: LK-2067 | B74: 22.07.2026 | C74: Anna Dubois | D74: netherlands | E74: coffee grinder | F74: 2 | G74: EUR 39.95 | H74: CARD
A75: LK-2068 | B75: 46226 | C75: MARIE VOS | D75: germany | E75: ceramic mug set (4) | F75: 1 | G75: €24,95 | H75: Paypal
A76: LK-2069 | B76: 46226 | C76: Anna Peters | D76: Nederland | E76: ceramic mug set (4) | F76: 1 | G76: 24.95 | H76: Card
A77: LK-2070 | B77: 2026-07-23 | C77: emma jansen | D77: NL | E77: FRENCH PRESS 1L | F77: 1 | G77: €29,95 | H77: ideal
A78: LK-2071 | B78: 46229 | C78: Sophie Bos | D78: Nederland | E78: linen tea towels | F78: 1 | G78: EUR 12.95 | H78: Paypal
A79: LK-2072 | B79: 46229 | C79: levi mulder | D79: België | E79: French Press 1L | F79: 1 pcs | G79: €29,95 | H79: Card
A80: LK-2073 | B80: 26/07/2026 | C80: Noah Martin | D80: netherlands | E80: ceramic mug set (4) | F80: 2 | G80: 24.95 | H80: Card
A81: LK-2074 | B81: 26 Jul 2026 | C81: Sem Peters | D81: BE | E81: pour-over kettle | F81: 4 | G81: 49 | H81: paypal
A82: LK-2075 | B82: 46229 | C82: Eva Jansen | D82: Netherlands | E82: FRENCH PRESS 1L | F82: 3 | G82: EUR 29.95 | H82: ideal
A83: LK-2076 | B83: 2026-07-27 | C83: Lena Smit | D83: DE | E83: COFFEE GRINDER | F83: 1 | G83: 39.95 | H83: CARD
A84: LK-2077 | B84: 46230 | C84: julia hendriks | D84: DE | E84: Cast-Iron Pan 26cm | F84: 1 | G84: 44.95 | H84: card
A85: LK-2078 | B85: 2026-07-27 | C85: Emma Schmidt | D85: Deutschland | E85: Oak Cutting Board | F85: 1 | G85: EUR 34.00 | H85: Paypal
A86: LK-2079 | B86: 28/07/2026 | C86: Noah Dubois | D86: france | E86: FRENCH PRESS 1L | F86: 2 | G86: EUR 29.95 | H86: CARD
A87: LK-2080 | B87: 28/07/2026 | C87: Claire Meijer | D87: DE | E87: French Press 1 L | F87: 2 | G87: 2995 | H87: Card
A88: LK-2081 | B88: 30 Jul 2026 | C88: Lea de Vries | D88: Netherlands | E88: coffee grinder | F88: 1 | G88: €39,95 | H88: iDeal
A89: LK-2082 | B89: 46233 | C89: Lotte Müller | D89: Deutschland | E89: Mug Set (4) | F89: 2 | G89: 24.95 | H89: paypal
A90: LK-2083 | B90: 46233 | C90: Levi Hendriks | D90: Netherlands | E90: Cast Iron Pan 26cm | F90: 4 | G90: €44,95 | H90: paypal
A91: LK-2084 | B91: 30/07/2026 | C91: Levi Dubois | D91: Holland | E91: COFFEE GRINDER | F91: 3 | G91: EUR 39.95 | H91: CARD
A92: LK-2085 | B92: 2026-07-31 | C92: Sara Schmidt | D92: NL | E92: Ceramic mug set x4 | F92: 1 | G92: 24.95 | H92: CARD
A93: LK-2086 | B93: August 1, 2026 | C93: EMMA BAKKER | D93: netherlands | E93: ceramic mug set (4) | G93: 24.95 | H93: Paypal
A94: LK-2087 | B94: 1 Aug 2026 | C94: lotte jansen | D94: netherlands | E94: Coffee Grinder | F94: 1 | G94: EUR 39.95 | H94: card
A95: LK-2088 | B95: 01/08/2026 | C95: Noah Dubois | D95: Nederland | E95: linen tea towels | F95: 1 | G95: EUR 12.95 | H95: IDEAL
A96: LK-2089 | B96: 2026-08-01 | C96: Eva Hendriks | D96: Deutschland | E96: pour-over kettle | F96: 2 | G96: 49 | H96: Paypal
A97: LK-2090 | B97: 02.08.2026 | C97: Eva Müller | D97: belgium | E97: Glass Teapot | F97: 1 | G97: €27,50 | H97: Credit card
A98: LK-2091 | B98: August 2, 2026 | C98: Emma Jansen | D98: france | E98: Linen Tea Towels (2) | F98: 1 | G98: 12.95 | H98: card
A99: LK-2092 | B99: August 3, 2026 | C99: Anna Smit | D99: Netherlands | E99: Mug Set (4) | F99: 1 | G99: 24.95 | H99: IDEAL
A100: LK-2093 | B100: 03.08.2026 | C100: Noah Müller | D100: belgium | E100: Oak Cutting Board | F100: 1 | G100: EUR 34.00 | H100: Credit card
A101: LK-2094 | B101: 46237 | C101: Anna Mulder | D101: NL | E101: Oak Chopping Board | F101: 2 | G101: 34 | H101: Credit card
A102: LK-2095 | B102: 03/08/2026 | C102: Liam Visser | D102: germany | E102: Linen Tea Towels (2) | F102: 2 | G102: €12,95 | H102: iDeal
...
